crcpy/__init__.py
crcpy/libcrclib.dll
crcpy/libcrclib.dylib
crcpy/libcrclib.so
crcpy-0.1.dist-info/METADATA
crcpy-0.1.dist-info/WHEEL
crcpy-0.1.dist-info/top_level.txt
crcpy-0.1.dist-info/RECORD
