Metadata-Version: 2.1
Name: crcpy
Version: 0.1
Summary: Node' crc32sum library bind to python
Home-page: UNKNOWN
Author: Zerolevel team
Author-email: zerolevel@gmail.com
License: UNKNOWN
Platform: UNKNOWN
Classifier: Programming Language :: Python :: 3
Classifier: License :: OSI Approved :: MIT License
Classifier: Operating System :: OS Independent
